{
 "result":"success",
 "documentation":"https://www.exchangerate-api.com/docs",
 "terms_of_use":"https://www.exchangerate-api.com/terms",
 "time_last_update_unix":1783641601,
 "time_last_update_utc":"Fri, 10 Jul 2026 00:00:01 +0000",
 "time_next_update_unix":1783728001,
 "time_next_update_utc":"Sat, 11 Jul 2026 00:00:01 +0000",
 "base_code":"BDT",
 "conversion_rates":{
  "BDT":1,
  "AED":0.02980,
  "AFN":0.5304,
  "ALL":0.6670,
  "AMD":2.9762,
  "ANG":0.01453,
  "AOA":7.6048,
  "ARS":12.0980,
  "AUD":0.01169,
  "AWG":0.01453,
  "AZN":0.01380,
  "BAM":0.01388,
  "BBD":0.01623,
  "BGN":0.01388,
  "BHD":0.003051,
  "BIF":24.2254,
  "BMD":0.008115,
  "BND":0.01049,
  "BOB":0.08053,
  "BRL":0.04162,
  "BSD":0.008115,
  "BTN":0.7744,
  "BWP":0.1111,
  "BYN":0.02324,
  "BZD":0.01623,
  "CAD":0.01150,
  "CDF":18.7425,
  "CHF":0.006548,
  "CLF":0.00019219,
  "CLP":7.5967,
  "CNH":0.05516,
  "CNY":0.05519,
  "COP":27.1254,
  "CRC":3.6929,
  "CUP":0.1947,
  "CVE":0.7827,
  "CZK":0.1721,
  "DJF":1.4421,
  "DKK":0.05296,
  "DOP":0.4774,
  "DZD":1.0807,
  "EGP":0.4026,
  "ERN":0.1217,
  "ETB":1.2937,
  "EUR":0.007099,
  "FJD":0.01816,
  "FKP":0.006054,
  "FOK":0.05294,
  "GBP":0.006054,
  "GEL":0.02135,
  "GGP":0.006054,
  "GHS":0.09285,
  "GIP":0.006054,
  "GMD":0.6026,
  "GNF":71.2155,
  "GTQ":0.06192,
  "GYD":1.6973,
  "HKD":0.06360,
  "HNL":0.2172,
  "HRK":0.05348,
  "HTG":1.0619,
  "HUF":2.5366,
  "IDR":146.5570,
  "ILS":0.02451,
  "IMP":0.006054,
  "INR":0.7744,
  "IQD":10.6271,
  "IRR":11164.5985,
  "ISK":1.0176,
  "JEP":0.006054,
  "JMD":1.2865,
  "JOD":0.005753,
  "JPY":1.3178,
  "KES":1.0487,
  "KGS":0.7098,
  "KHR":32.7825,
  "KID":0.01169,
  "KMF":3.4922,
  "KRW":12.2281,
  "KWD":0.002490,
  "KYD":0.006762,
  "KZT":3.7923,
  "LAK":181.3030,
  "LBP":726.2512,
  "LKR":2.7215,
  "LRD":1.4720,
  "LSL":0.1326,
  "LYD":0.05195,
  "MAD":0.07597,
  "MDL":0.1424,
  "MGA":34.5504,
  "MKD":0.4376,
  "MMK":17.0641,
  "MNT":29.1033,
  "MOP":0.06550,
  "MRU":0.3244,
  "MUR":0.3830,
  "MVR":0.1255,
  "MWK":14.1408,
  "MXN":0.1424,
  "MYR":0.03310,
  "MZN":0.5177,
  "NAD":0.1326,
  "NGN":11.1359,
  "NIO":0.2986,
  "NOK":0.07894,
  "NPR":1.2390,
  "NZD":0.01411,
  "OMR":0.003120,
  "PAB":0.008115,
  "PEN":0.02763,
  "PGK":0.03567,
  "PHP":0.4995,
  "PKR":2.2557,
  "PLN":0.03068,
  "PYG":49.1983,
  "QAR":0.02954,
  "RON":0.03718,
  "RSD":0.8335,
  "RUB":0.6182,
  "RWF":11.9178,
  "SAR":0.03043,
  "SBD":0.06534,
  "SCR":0.1153,
  "SDG":4.1524,
  "SEK":0.07846,
  "SGD":0.01049,
  "SHP":0.006054,
  "SLE":0.1972,
  "SLL":197.2340,
  "SOS":4.6395,
  "SRD":0.3058,
  "SSP":38.3629,
  "STN":0.1739,
  "SYP":0.9884,
  "SZL":0.1326,
  "THB":0.2711,
  "TJS":0.07501,
  "TMT":0.02840,
  "TND":0.02389,
  "TOP":0.01951,
  "TRY":0.3807,
  "TTD":0.05509,
  "TVD":0.01169,
  "TWD":0.2609,
  "TZS":21.3649,
  "UAH":0.3615,
  "UGX":29.9294,
  "USD":0.008115,
  "UYU":0.3265,
  "UZS":96.6226,
  "VES":5.7588,
  "VND":212.4945,
  "VUV":0.9798,
  "WST":0.02240,
  "XAF":4.6563,
  "XCD":0.02191,
  "XCG":0.01453,
  "XDR":0.005973,
  "XOF":4.6563,
  "XPF":0.8471,
  "YER":1.9302,
  "ZAR":0.1326,
  "ZMW":0.1479,
  "ZWG":0.2171,
  "ZWL":0.2171
 }
}