{
 "result":"success",
 "documentation":"https://www.exchangerate-api.com/docs",
 "terms_of_use":"https://www.exchangerate-api.com/terms",
 "time_last_update_unix":1780099202,
 "time_last_update_utc":"Sat, 30 May 2026 00:00:02 +0000",
 "time_next_update_unix":1780185602,
 "time_next_update_utc":"Sun, 31 May 2026 00:00:02 +0000",
 "base_code":"BDT",
 "conversion_rates":{
  "BDT":1,
  "AED":0.02992,
  "AFN":0.5146,
  "ALL":0.6684,
  "AMD":2.9959,
  "ANG":0.01458,
  "AOA":7.7506,
  "ARS":11.4911,
  "AUD":0.01134,
  "AWG":0.01458,
  "AZN":0.01384,
  "BAM":0.01367,
  "BBD":0.01630,
  "BGN":0.01367,
  "BHD":0.003064,
  "BIF":24.2417,
  "BMD":0.008148,
  "BND":0.01040,
  "BOB":0.05635,
  "BRL":0.04113,
  "BSD":0.008148,
  "BTN":0.7785,
  "BWP":0.1131,
  "BYN":0.02235,
  "BZD":0.01630,
  "CAD":0.01124,
  "CDF":18.6357,
  "CHF":0.006364,
  "CLF":0.00018448,
  "CLP":7.2919,
  "CNH":0.05512,
  "CNY":0.05526,
  "COP":29.7446,
  "CRC":3.6912,
  "CUP":0.1956,
  "CVE":0.7707,
  "CZK":0.1698,
  "DJF":1.4481,
  "DKK":0.05214,
  "DOP":0.4816,
  "DZD":1.0829,
  "EGP":0.4255,
  "ERN":0.1222,
  "ETB":1.3001,
  "EUR":0.006989,
  "FJD":0.01808,
  "FKP":0.006054,
  "FOK":0.05214,
  "GBP":0.006054,
  "GEL":0.02171,
  "GGP":0.006054,
  "GHS":0.09558,
  "GIP":0.006054,
  "GMD":0.6044,
  "GNF":71.3959,
  "GTQ":0.06211,
  "GYD":1.7042,
  "HKD":0.06385,
  "HNL":0.2166,
  "HRK":0.05266,
  "HTG":1.0672,
  "HUF":2.4793,
  "IDR":145.2990,
  "ILS":0.02296,
  "IMP":0.006054,
  "INR":0.7785,
  "IQD":10.6729,
  "IRR":10749.2754,
  "ISK":1.0032,
  "JEP":0.006054,
  "JMD":1.2838,
  "JOD":0.005777,
  "JPY":1.2977,
  "KES":1.0546,
  "KGS":0.7131,
  "KHR":32.7641,
  "KID":0.01134,
  "KMF":3.4384,
  "KRW":12.2815,
  "KWD":0.002489,
  "KYD":0.006790,
  "KZT":3.9485,
  "LAK":178.6740,
  "LBP":729.2499,
  "LKR":2.6767,
  "LRD":1.4842,
  "LSL":0.1323,
  "LYD":0.05177,
  "MAD":0.07495,
  "MDL":0.1411,
  "MGA":34.2552,
  "MKD":0.4314,
  "MMK":17.1020,
  "MNT":29.2523,
  "MOP":0.06577,
  "MRU":0.3257,
  "MUR":0.3868,
  "MVR":0.1258,
  "MWK":14.2330,
  "MXN":0.1411,
  "MYR":0.03234,
  "MZN":0.5212,
  "NAD":0.1323,
  "NGN":11.1705,
  "NIO":0.2992,
  "NOK":0.07531,
  "NPR":1.2455,
  "NZD":0.01366,
  "OMR":0.003133,
  "PAB":0.008148,
  "PEN":0.02776,
  "PGK":0.03552,
  "PHP":0.5005,
  "PKR":2.2712,
  "PLN":0.02955,
  "PYG":49.9390,
  "QAR":0.02966,
  "RON":0.03676,
  "RSD":0.8225,
  "RUB":0.5794,
  "RWF":11.9729,
  "SAR":0.03056,
  "SBD":0.06515,
  "SCR":0.1191,
  "SDG":4.7243,
  "SEK":0.07532,
  "SGD":0.01040,
  "SHP":0.006054,
  "SLE":0.2005,
  "SLL":200.4595,
  "SOS":4.6557,
  "SRD":0.3030,
  "SSP":38.2637,
  "STN":0.1712,
  "SYP":0.9211,
  "SZL":0.1323,
  "THB":0.2647,
  "TJS":0.07522,
  "TMT":0.02852,
  "TND":0.02365,
  "TOP":0.01940,
  "TRY":0.3740,
  "TTD":0.05532,
  "TVD":0.01134,
  "TWD":0.2556,
  "TZS":21.4711,
  "UAH":0.3605,
  "UGX":30.7291,
  "USD":0.008148,
  "UYU":0.3259,
  "UZS":97.6762,
  "VES":4.5175,
  "VND":213.5247,
  "VUV":0.9680,
  "WST":0.02210,
  "XAF":4.5846,
  "XCD":0.02200,
  "XCG":0.01458,
  "XDR":0.005958,
  "XOF":4.5846,
  "XPF":0.8340,
  "YER":1.9431,
  "ZAR":0.1323,
  "ZMW":0.1502,
  "ZWG":0.2193,
  "ZWL":0.2193
 }
}